mc_autofisher/__init__.py
mc_autofisher/__main__.py
mc_autofisher/config.json
mc_autofisher/fisher.py
mc_autofisher/screengrabber.py
tests/__init__.py
tests/fisher_test.py
mc_autofisher-1.2.0.dist-info/LICENSE
mc_autofisher-1.2.0.dist-info/METADATA
mc_autofisher-1.2.0.dist-info/WHEEL
mc_autofisher-1.2.0.dist-info/top_level.txt
mc_autofisher-1.2.0.dist-info/RECORD
