Metadata-Version: 2.1
Name: mc-autofisher
Version: 1.2.0
Summary: Automated fishing program for Minecraft
Home-page: https://github.com/r-best/MinecraftAutoFisher
Author: Robert Best
Author-email: bobbyisbest3@gmail.com
License: gpl-3.0
Keywords: python python3 minecraft
Platform: UNKNOWN
Classifier: Programming Language :: Python :: 3.6
Requires-Dist: pyscreenshot (>=0.4.2)
Requires-Dist: Pillow (>=5.3.0)
Requires-Dist: pytesseract (>=0.2.5)
Requires-Dist: pynput (>=1.4)
Requires-Dist: python-levenshtein (>=0.12.0)
Requires-Dist: pytest (>=3.9.2)
